academic_chatgpt/__main__.py
academic_chatgpt/check_proxy.py
academic_chatgpt/config.py
academic_chatgpt/crazy_functions/func_template.py
academic_chatgpt/crazy_functions/generate_func_comment.py
academic_chatgpt/crazy_functions/parse_source_code.py
academic_chatgpt/crazy_functions/read_abstract.py
academic_chatgpt/functional.py
academic_chatgpt/functional_crazy.py
academic_chatgpt/predict.py
academic_chatgpt/show_math.py
academic_chatgpt/theme.py
academic_chatgpt/utils.py
academic_chatgpt-0.4.1.dist-info/LICENSE
academic_chatgpt-0.4.1.dist-info/METADATA
academic_chatgpt-0.4.1.dist-info/WHEEL
academic_chatgpt-0.4.1.dist-info/entry_points.txt
academic_chatgpt-0.4.1.dist-info/RECORD
