Metadata-Version: 2.1
Name: academic-chatgpt
Version: 0.4.1
Summary: chatgpt for academic
License: GPLv3
Author: Yangyang Li
Author-email: yangyang.li@northwestern.edu
Requires-Python: >=3.9,<4.0
Classifier: Development Status :: 2 - Pre-Alpha
Classifier: Environment :: Console
Classifier: License :: Other/Proprietary License
Classifier: Programming Language :: Python :: 3
Classifier: Programming Language :: Python :: 3.9
Classifier: Programming Language :: Python :: 3.10
Classifier: Programming Language :: Python :: 3.11
Classifier: Programming Language :: Python :: 3.10
Classifier: Programming Language :: Python :: 3.9
Requires-Dist: gradio (>=3.23.0,<4.0.0)
Requires-Dist: latex2mathml (>=3.75.1,<4.0.0)
Requires-Dist: loguru (>=0.6.0,<0.7.0)
Requires-Dist: mdtex2html (>=1.2.0,<2.0.0)
Requires-Dist: pydantic (>=1.10.7,<2.0.0)
Requires-Dist: requests (>=2.28.2,<3.0.0)
Requires-Dist: toml (>=0.10.2,<0.11.0)
